ga2/__init__.py
ga2/gaDisc.py
ga2/gaUtils/AgentClass.py
ga2/gaUtils/__init__.py
ga2/gaUtils/gaDaemon.py
ga2-1.0.0.post1.dist-info/LICENSE
ga2-1.0.0.post1.dist-info/METADATA
ga2-1.0.0.post1.dist-info/WHEEL
ga2-1.0.0.post1.dist-info/top_level.txt
ga2-1.0.0.post1.dist-info/RECORD
