Metadata-Version: 2.1
Name: ga2
Version: 1.0.0.post1
Summary: A simple robust Genetic Algorithm utility
Home-page: https://github.com/yashasbharadwaj111/GeneticAlgorithm
Author: Yashas ND
Author-email: yashasbharadwaj111@gmail.com
License: UNKNOWN
Platform: UNKNOWN
Classifier: License :: OSI Approved :: MIT License
Classifier: Programming Language :: Python :: 3.6
Classifier: Topic :: Scientific/Engineering :: Artificial Life
Classifier: Intended Audience :: Science/Research
Classifier: Development Status :: 4 - Beta
Classifier: Operating System :: POSIX :: Linux
